src/__init__.py
src/helpers.py
src/main.py
runllama-0.2.0.dist-info/LICENSE
runllama-0.2.0.dist-info/METADATA
runllama-0.2.0.dist-info/WHEEL
runllama-0.2.0.dist-info/entry_points.txt
runllama-0.2.0.dist-info/top_level.txt
runllama-0.2.0.dist-info/RECORD
