Metadata-Version: 2.2
Name: runllama
Version: 0.2.0
Summary: Simple CLI runner for Ollama (LLM) models
Author: Believe Manasseh
Author-email: Manasseh <believemanasseh@gmail.com>
Maintainer-email: Manasseh <believemanasseh@gmail.com>
License: MIT
Project-URL: homepage, https://github.com/believemanasseh/RunLlama
Project-URL: issues, https://github.com/believemanasseh/RunLlama/issues
Keywords: ollama,llama,large language model (LLM),ai,artificial intelligence,machine learning,natural language processing (NLP),conversational ai
Classifier: Programming Language :: Python :: 3.10
Classifier: Programming Language :: Python :: 3.11
Classifier: Programming Language :: Python :: 3.12
Classifier: Programming Language :: Python :: 3.13
Classifier: Programming Language :: Python :: 3.14
Classifier: Operating System :: OS Independent
Classifier: Development Status :: 5 - Production/Stable
Requires-Python: >=3.10
License-File: LICENSE
Requires-Dist: ollama==0.4.7
Requires-Dist: click==8.1.8
Dynamic: author
Dynamic: classifier
Dynamic: requires-python
